{
  "step1_concentration": [
    {
      "d": 50,
      "mean_R": 100.37456631043793,
      "theory_mean": 100.0,
      "rel_fluct": 0.20158481370727668,
      "theory_rel": 0.2,
      "ratio": 1.0079240685363833
    },
    {
      "d": 100,
      "mean_R": 200.88588800387387,
      "theory_mean": 200.0,
      "rel_fluct": 0.14195489794745295,
      "theory_rel": 0.1414213562373095,
      "ratio": 1.003772709612883
    },
    {
      "d": 500,
      "mean_R": 999.634976358864,
      "theory_mean": 1000.0,
      "rel_fluct": 0.06257605493248244,
      "theory_rel": 0.06324555320336758,
      "ratio": 0.9894143028722928
    },
    {
      "d": 1000,
      "mean_R": 2001.7615609506838,
      "theory_mean": 2000.0,
      "rel_fluct": 0.04524333959117342,
      "theory_rel": 0.044721359549995794,
      "ratio": 1.0116718285497133
    },
    {
      "d": 5000,
      "mean_R": 10001.018733754674,
      "theory_mean": 10000.0,
      "rel_fluct": 0.019995410699062296,
      "theory_rel": 0.02,
      "ratio": 0.9997705349531147
    }
  ],
  "step2_gumbel_minima": [
    {
      "d": 50,
      "n_per_class": 50,
      "gumbel_ks_stat": 0.08065954867015318,
      "gumbel_ks_p": 2.0011123366585878e-17,
      "normal_ks_stat": 0.018074273951673825,
      "normal_ks_p": 0.2775731256301064,
      "gumbel_wins": false
    },
    {
      "d": 100,
      "n_per_class": 50,
      "gumbel_ks_stat": 0.08042765571522204,
      "gumbel_ks_p": 2.5058338063270242e-17,
      "normal_ks_stat": 0.016184096699613848,
      "normal_ks_p": 0.40743567840102457,
      "gumbel_wins": false
    },
    {
      "d": 500,
      "n_per_class": 50,
      "gumbel_ks_stat": 0.06136567113166802,
      "gumbel_ks_p": 2.904606066149638e-10,
      "normal_ks_stat": 0.017609212419248732,
      "normal_ks_p": 0.3064417751519821,
      "gumbel_wins": false
    },
    {
      "d": 1000,
      "n_per_class": 50,
      "gumbel_ks_stat": 0.05442511049459409,
      "gumbel_ks_p": 3.649379388318745e-08,
      "normal_ks_stat": 0.020310527706309922,
      "normal_ks_p": 0.16594247210734192,
      "gumbel_wins": false
    }
  ],
  "step3_logistic_difference": [
    {
      "K": 10,
      "kappa_target": 0.2,
      "kappa_actual": 0.18,
      "d": 500,
      "n_per_class": 30,
      "knn_acc": 0.9995,
      "q_obs": 0.9994444444444445,
      "q_theory": 0.515806119945407,
      "q_error": 0.48363832449903743,
      "margin_mean": 132.82988574483107,
      "margin_std": 39.82466671359085,
      "logistic_loc": 132.70885738429752,
      "logistic_scale": 22.62565022797975,
      "logistic_ks_p": 0.6619510533738356,
      "normal_ks_p": 0.9665919534338893,
      "logistic_wins": false
    },
    {
      "K": 10,
      "kappa_target": 0.5,
      "kappa_actual": 0.45,
      "d": 500,
      "n_per_class": 30,
      "knn_acc": 1.0,
      "q_obs": 1.0,
      "q_theory": 0.5394463251293178,
      "q_error": 0.4605536748706822,
      "margin_mean": 398.9925551282207,
      "margin_std": 48.83000261015899,
      "logistic_loc": 399.27587063964336,
      "logistic_scale": 27.843467257816357,
      "logistic_ks_p": 0.23348640448523728,
      "normal_ks_p": 0.7879878092209089,
      "logistic_wins": false
    },
    {
      "K": 10,
      "kappa_target": 1.0,
      "kappa_actual": 0.9000000000000002,
      "d": 500,
      "n_per_class": 30,
      "knn_acc": 1.0,
      "q_obs": 1.0,
      "q_theory": 0.5784046557403111,
      "q_error": 0.4215953442596889,
      "margin_mean": 851.9284458579158,
      "margin_std": 61.74499981946498,
      "logistic_loc": 852.3809212853669,
      "logistic_scale": 35.35469924522531,
      "logistic_ks_p": 0.27679639913200327,
      "normal_ks_p": 0.9726103463717558,
      "logistic_wins": false
    },
    {
      "K": 10,
      "kappa_target": 2.0,
      "kappa_actual": 1.8,
      "d": 500,
      "n_per_class": 30,
      "knn_acc": 1.0,
      "q_obs": 1.0,
      "q_theory": 0.653046037940768,
      "q_error": 0.346953962059232,
      "margin_mean": 1778.2296824937323,
      "margin_std": 82.53359843374457,
      "logistic_loc": 1778.3051495192735,
      "logistic_scale": 47.21637718129567,
      "logistic_ks_p": 0.3687871560188952,
      "normal_ks_p": 0.8197258498405289,
      "logistic_wins": false
    },
    {
      "K": 50,
      "kappa_target": 0.2,
      "kappa_actual": 0.196,
      "d": 500,
      "n_per_class": 30,
      "knn_acc": 0.998,
      "q_obs": 0.9979591836734694,
      "q_theory": 0.5070705964450539,
      "q_error": 0.49088858722841544,
      "margin_mean": 102.703218268405,
      "margin_std": 36.24971282975255,
      "logistic_loc": 102.82879757685735,
      "logistic_scale": 20.597557073792206,
      "logistic_ks_p": 0.3632548525312319,
      "normal_ks_p": 0.7758373575724914,
      "logistic_wins": false
    },
    {
      "K": 50,
      "kappa_target": 0.5,
      "kappa_actual": 0.49,
      "d": 500,
      "n_per_class": 30,
      "knn_acc": 1.0,
      "q_obs": 1.0,
      "q_theory": 0.5176703075150118,
      "q_error": 0.48232969248498825,
      "margin_mean": 360.7111101227734,
      "margin_std": 46.16437073209022,
      "logistic_loc": 360.97902214932884,
      "logistic_scale": 26.10421191698429,
      "logistic_ks_p": 0.735255749654445,
      "normal_ks_p": 0.5205462560707046,
      "logistic_wins": true
    },
    {
      "K": 50,
      "kappa_target": 1.0,
      "kappa_actual": 0.9800000000000002,
      "d": 500,
      "n_per_class": 30,
      "knn_acc": 1.0,
      "q_obs": 1.0,
      "q_theory": 0.5352965311073327,
      "q_error": 0.46470346889266734,
      "margin_mean": 804.4090581634957,
      "margin_std": 56.66607575409768,
      "logistic_loc": 804.5928101949074,
      "logistic_scale": 32.34167764865076,
      "logistic_ks_p": 0.598792467687779,
      "normal_ks_p": 0.9594608336566645,
      "logistic_wins": false
    },
    {
      "K": 50,
      "kappa_target": 2.0,
      "kappa_actual": 1.96,
      "d": 500,
      "n_per_class": 30,
      "knn_acc": 1.0,
      "q_obs": 1.0,
      "q_theory": 0.570243014550411,
      "q_error": 0.42975698544958896,
      "margin_mean": 1714.3289431418507,
      "margin_std": 76.10831577306864,
      "logistic_loc": 1714.6668437594271,
      "logistic_scale": 43.2205011582722,
      "logistic_ks_p": 0.4716263691976028,
      "normal_ks_p": 0.8709427538053036,
      "logistic_wins": false
    },
    {
      "K": 150,
      "kappa_target": 0.2,
      "kappa_actual": 0.19866666666666666,
      "d": 500,
      "n_per_class": 30,
      "knn_acc": 0.9915,
      "q_obs": 0.9914429530201343,
      "q_theory": 0.5040823921852154,
      "q_error": 0.48736056083491885,
      "margin_mean": 86.79930992192288,
      "margin_std": 35.90020029780641,
      "logistic_loc": 86.85108508752106,
      "logistic_scale": 20.447049674896228,
      "logistic_ks_p": 0.27915075517722454,
      "normal_ks_p": 0.9178360626319721,
      "logistic_wins": false
    },
    {
      "K": 150,
      "kappa_target": 0.5,
      "kappa_actual": 0.4966666666666665,
      "d": 500,
      "n_per_class": 30,
      "knn_acc": 1.0,
      "q_obs": 1.0,
      "q_theory": 0.5102047899690252,
      "q_error": 0.4897952100309748,
      "margin_mean": 338.84513808285607,
      "margin_std": 43.161357388861255,
      "logistic_loc": 338.9818046677966,
      "logistic_scale": 24.6467054328863,
      "logistic_ks_p": 0.3994556433958878,
      "normal_ks_p": 0.9369885974664777,
      "logistic_wins": false
    },
    {
      "K": 150,
      "kappa_target": 1.0,
      "kappa_actual": 0.9933333333333333,
      "d": 500,
      "n_per_class": 30,
      "knn_acc": 1.0,
      "q_obs": 1.0,
      "q_theory": 0.5204010818479593,
      "q_error": 0.4795989181520407,
      "margin_mean": 777.5660989322329,
      "margin_std": 55.9958880520236,
      "logistic_loc": 777.6781792925817,
      "logistic_scale": 31.94951936437381,
      "logistic_ks_p": 0.3697403011989252,
      "normal_ks_p": 0.7846132148469204,
      "logistic_wins": false
    },
    {
      "K": 150,
      "kappa_target": 2.0,
      "kappa_actual": 1.9866666666666666,
      "d": 500,
      "n_per_class": 30,
      "knn_acc": 1.0,
      "q_obs": 1.0,
      "q_theory": 0.5407343484779195,
      "q_error": 0.45926565152208054,
      "margin_mean": 1676.1080963641843,
      "margin_std": 75.40669354104462,
      "logistic_loc": 1676.7932823912315,
      "logistic_scale": 43.0989115985786,
      "logistic_ks_p": 0.1664280995502796,
      "normal_ks_p": 0.881016191150137,
      "logistic_wins": false
    }
  ],
  "step4_sqrtK_scaling": [
    {
      "K": 4,
      "q_obs": 1.0,
      "logit_q": 23.025850929940457,
      "q_pred_sqrtK": 0.6224593312018546,
      "q_pred_K": 0.5621765008857981,
      "q_pred_logK": 0.6729036812101264,
      "err_sqrtK": 0.3775406687981454,
      "err_K": 0.43782349911420193,
      "err_logK": 0.32709631878987355
    },
    {
      "K": 8,
      "q_obs": 1.0,
      "logit_q": 23.025850929940457,
      "q_pred_sqrtK": 0.5874790008396098,
      "q_pred_K": 0.5312093733737563,
      "q_pred_logK": 0.6179599838719827,
      "err_sqrtK": 0.4125209991603902,
      "err_K": 0.4687906266262437,
      "err_logK": 0.3820400161280173
    },
    {
      "K": 16,
      "q_obs": 1.0,
      "logit_q": 23.025850929940457,
      "q_pred_sqrtK": 0.5621765008857981,
      "q_pred_K": 0.5156199157230156,
      "q_pred_logK": 0.5892035226190117,
      "err_sqrtK": 0.43782349911420193,
      "err_K": 0.4843800842769844,
      "err_logK": 0.41079647738098835
    },
    {
      "K": 32,
      "q_obs": 1.0,
      "logit_q": 23.025850929940457,
      "q_pred_sqrtK": 0.544079443349226,
      "q_pred_K": 0.5078118642792044,
      "q_pred_logK": 0.5716384203813912,
      "err_sqrtK": 0.455920556650774,
      "err_K": 0.49218813572079556,
      "err_logK": 0.42836157961860877
    },
    {
      "K": 64,
      "q_obs": 1.0,
      "logit_q": 23.025850929940457,
      "q_pred_sqrtK": 0.5312093733737563,
      "q_pred_K": 0.5039061705290805,
      "q_pred_logK": 0.5598243380400092,
      "err_sqrtK": 0.4687906266262437,
      "err_K": 0.4960938294709195,
      "err_logK": 0.4401756619599908
    },
    {
      "K": 128,
      "q_obs": 1.0,
      "logit_q": 23.025850929940457,
      "q_pred_sqrtK": 0.5220827120180694,
      "q_pred_K": 0.5019531150659532,
      "q_pred_logK": 0.5513432096473292,
      "err_sqrtK": 0.47791728798193056,
      "err_K": 0.4980468849340468,
      "err_logK": 0.4486567903526708
    }
  ],
  "step4_summary": {
    "err_sqrtK": 0.4384189397219476,
    "err_K": 0.4795538433571987,
    "err_logK": 0.40618780737169163,
    "best": "log(K)"
  },
  "step5_eta_correction": [
    {
      "alpha": 0.0,
      "eta": 1.0,
      "q_obs": 1.0,
      "q_isotropic_pred": 0.5352965311073327,
      "q_delta": 0.46470346889266734
    },
    {
      "alpha": 0.5,
      "eta": 0.5515966798866218,
      "q_obs": 1.0,
      "q_isotropic_pred": 0.5352965311073327,
      "q_delta": 0.46470346889266734
    },
    {
      "alpha": 1.0,
      "eta": 0.05617071914063468,
      "q_obs": 1.0,
      "q_isotropic_pred": 0.5352965311073327,
      "q_delta": 0.46470346889266734
    },
    {
      "alpha": 1.5,
      "eta": 0.010590888257530868,
      "q_obs": 1.0,
      "q_isotropic_pred": 0.5352965311073327,
      "q_delta": 0.46470346889266734
    },
    {
      "alpha": 2.0,
      "eta": 0.004987860997393168,
      "q_obs": 0.9984693877551021,
      "q_isotropic_pred": 0.5352965311073327,
      "q_delta": 0.4631728566477694
    },
    {
      "alpha": 3.0,
      "eta": 0.002840607173352777,
      "q_obs": 0.9984693877551021,
      "q_isotropic_pred": 0.5352965311073327,
      "q_delta": 0.4631728566477694
    }
  ],
  "step5_summary": {
    "rho": 0.8280786712108252,
    "p": 0.04179468045604518
  },
  "scorecard": {
    "passes": 2,
    "total": 6,
    "checks": [
      {
        "criterion": "Distance concentration matches theory (ratio~1.0)",
        "passed": true,
        "value": "avg ratio=1.003"
      },
      {
        "criterion": "Gumbel fits NN minima >= 50% of cases",
        "passed": false,
        "value": "0%"
      },
      {
        "criterion": "Logistic fits margin differences >= 50% of cases",
        "passed": false,
        "value": "8%"
      },
      {
        "criterion": "sigmoid(kappa/sqrt(K)) MAE < 0.05",
        "passed": false,
        "value": "MAE=0.4580"
      },
      {
        "criterion": "sqrt(K) is the best normalization",
        "passed": false,
        "value": "log(K)"
      },
      {
        "criterion": "eta positively correlates with q (rho > 0.5)",
        "passed": true,
        "value": "rho=0.828"
      }
    ]
  }
}